Tool.py
huanglinflask/__init__.py
huanglinflask/config.py
huanglinflask/login.py
huanglinflask/p.py
huanglinflask-1.0.1.dist-info/METADATA
huanglinflask-1.0.1.dist-info/RECORD
huanglinflask-1.0.1.dist-info/WHEEL
huanglinflask-1.0.1.dist-info/top_level.txt
