Metadata-Version: 2.1
Name: huanglinflask
Version: 1.0.1
Summary: 这是一个练习的项目
Home-page: UNKNOWN
Author: huanglin
Author-email: ahkjgsdfv@qq.com
License: UNKNOWN
Platform: UNKNOWN
